django_health_check_view/__init__.py
django_health_check_view/_stub_settings.py
django_health_check_view/apps.py
django_health_check_view/serializers.py
django_health_check_view/settings.py
django_health_check_view/urls.py
django_health_check_view/views.py
django_health_check_view/providers/__init__.py
django_health_check_view/providers/base.py
django_health_check_view/providers/db.py
django_health_check_view-0.0.5.dist-info/LICENSE
django_health_check_view-0.0.5.dist-info/WHEEL
django_health_check_view-0.0.5.dist-info/METADATA
django_health_check_view-0.0.5.dist-info/RECORD
